mailreport/__init__.py
mailreport/mailreport.py
mailreport-1.0.1.dist-info/LICENSE.txt
mailreport-1.0.1.dist-info/METADATA
mailreport-1.0.1.dist-info/WHEEL
mailreport-1.0.1.dist-info/top_level.txt
mailreport-1.0.1.dist-info/RECORD
