Metadata-Version: 2.1
Name: mailreport
Version: 1.0.1
Summary: Python Pkg for sending autmated reports on email
Home-page: https://github.com/nit567esh/mailreport
Author: Nitesh Kumar
Author-email: nit567esh@gmail.com
License: UNKNOWN
Platform: UNKNOWN
Requires-Dist: pandas
